method/__init__.py
method/configuration.py
method/errors.py
method/method.py
method/resource.py
method/resources/CardProduct.py
method/resources/HealthCheck.py
method/resources/Merchant.py
method/resources/Report.py
method/resources/Webhook.py
method/resources/__init__.py
method/resources/Accounts/Account.py
method/resources/Accounts/Attributes.py
method/resources/Accounts/Balances.py
method/resources/Accounts/CardBrands.py
method/resources/Accounts/ExternalTypes.py
method/resources/Accounts/PaymentInstruments.py
method/resources/Accounts/Payoffs.py
method/resources/Accounts/Products.py
method/resources/Accounts/Sensitive.py
method/resources/Accounts/Subscriptions.py
method/resources/Accounts/Transactions.py
method/resources/Accounts/Types.py
method/resources/Accounts/Updates.py
method/resources/Accounts/VerificationSessions.py
method/resources/Accounts/__init__.py
method/resources/Elements/Element.py
method/resources/Elements/Token.py
method/resources/Elements/__init__.py
method/resources/Entities/Attributes.py
method/resources/Entities/Connect.py
method/resources/Entities/CreditScores.py
method/resources/Entities/Entity.py
method/resources/Entities/Identities.py
method/resources/Entities/Products.py
method/resources/Entities/Sensitive.py
method/resources/Entities/Subscriptions.py
method/resources/Entities/Types.py
method/resources/Entities/Vehicles.py
method/resources/Entities/VerificationSessions.py
method/resources/Entities/__init__.py
method/resources/Events/Event.py
method/resources/Events/__init__.py
method/resources/Opal/Opal.py
method/resources/Opal/Token.py
method/resources/Opal/__init__.py
method/resources/Payments/Payment.py
method/resources/Payments/Reversal.py
method/resources/Payments/__init__.py
method/resources/Simulate/Accounts.py
method/resources/Simulate/Attributes.py
method/resources/Simulate/CardBrand.py
method/resources/Simulate/Connect.py
method/resources/Simulate/CreditScores.py
method/resources/Simulate/Entities.py
method_python-2.1.1.dist-info/licenses/LICENSE
method_python-2.1.1.dist-info/METADATA
method_python-2.1.1.dist-info/WHEEL
method_python-2.1.1.dist-info/top_level.txt
method_python-2.1.1.dist-info/RECORD
